d2b_lwc/__init__.py
d2b_lwc/main.py
d2b_lwc-0.1.0.dist-info/WHEEL
d2b_lwc-0.1.0.dist-info/METADATA
d2b_lwc-0.1.0.dist-info/RECORD
