Metadata-Version: 2.1
Name: d2b-lwc
Version: 0.1.0
Summary: 
Author: Joshua OLulana
Author-email: joshua.olulana@data2bots.com
Requires-Python: >=3.8,<4.0
Classifier: Programming Language :: Python :: 3
Classifier: Programming Language :: Python :: 3.10
Classifier: Programming Language :: Python :: 3.8
Classifier: Programming Language :: Python :: 3.9
Requires-Dist: pandas (>=1.3.4,<2.0.0)
